prettify_xml/__init__.py
prettify_xml/formatter.py
prettify_xml-0.4.5.dist-info/LICENSE
prettify_xml-0.4.5.dist-info/METADATA
prettify_xml-0.4.5.dist-info/WHEEL
prettify_xml-0.4.5.dist-info/entry_points.txt
prettify_xml-0.4.5.dist-info/top_level.txt
prettify_xml-0.4.5.dist-info/RECORD
