Metadata-Version: 2.1
Name: prettify-xml
Version: 0.4.5
Summary: CLI for prettifying XML
Home-page: http://www.codeberg/cap_jmk/xml-formatter
Author: Julian M. Kleber
Author-email: julian.kleber@sail.black
Classifier: Programming Language :: Python :: 3
Classifier: License :: OSI Approved :: GNU General Public License v3 (GPLv3)
Classifier: Operating System :: OS Independent
Requires-Python: >=3.9
License-File: LICENSE
Requires-Dist: Click
